aims_immune/AIMS_notebook.ipynb
aims_immune/__init__.py
aims_immune/__main__.py
aims_immune/aims.kv
aims_immune/aims.py
aims_immune/aims_analysis.py
aims_immune/aims_classification.py
aims_immune/aims_cli.py
aims_immune/aims_loader.py
aims_immune/get_tests.py
aims_immune/launch_notebook.py
aims_immune/app_data/AA_interactionV1.csv
aims_immune/app_data/AA_interactionV2.csv
aims_immune/app_data/AA_interactionV3.csv
aims_immune/app_data/Poppins-Light.ttf
aims_immune/app_data/Poppins-Medium.ttf
aims_immune/app_data/background.png
aims_immune/app_data/butt_down.png
aims_immune/app_data/butt_up.png
aims_immune/app_data/error_load.ai
aims_immune/app_data/error_load.png
aims_immune/app_data/error_pos.png
aims_immune/app_data/new_props
aims_immune/app_data/old_props
aims_immune/app_data/property_names.txt
aims_immune/app_data/square_background.png
aims_immune/app_data/transparent.png
aims_immune/app_data/white.png
aims_immune/app_data/germline_data/ABC_prot.fasta
aims_immune/app_data/germline_data/HLAnames2.csv
aims_immune/app_data/germline_data/classII_alpha.fasta
aims_immune/app_data/germline_data/classII_beta.fasta
aims_immune/app_data/germline_data/classIIa_names.csv
aims_immune/app_data/germline_data/classIIb_names.csv
aims_immune/app_data/germline_data/traj_human_cdrs.csv
aims_immune/app_data/germline_data/trav_human_cdrs.csv
aims_immune/app_data/germline_data/trav_mouse_cdrs.csv
aims_immune/app_data/germline_data/trav_rhesus_cdrs.csv
aims_immune/app_data/germline_data/trbj_human_cdrs.csv
aims_immune/app_data/germline_data/trbv_human_cdrs.csv
aims_immune/app_data/germline_data/trbv_mouse_cdrs.csv
aims_immune/app_data/germline_data/trbv_rhesus_cdrs.csv
aims_immune/app_data/screens/0README
aims_immune/app_data/screens/ab_1.kv
aims_immune/app_data/screens/ab_10.kv
aims_immune/app_data/screens/ab_11.kv
aims_immune/app_data/screens/ab_12.kv
aims_immune/app_data/screens/ab_13.kv
aims_immune/app_data/screens/ab_14.kv
aims_immune/app_data/screens/ab_2.kv
aims_immune-0.9.4.dist-info/LICENSE
aims_immune-0.9.4.dist-info/METADATA
aims_immune-0.9.4.dist-info/WHEEL
aims_immune-0.9.4.dist-info/entry_points.txt
aims_immune-0.9.4.dist-info/top_level.txt
aims_immune-0.9.4.dist-info/RECORD
