Metadata-Version: 2.1
Name: aims-immune
Version: 0.9.4
Summary: A software for the analysis of immune repertoires
Author-email: Chris Boughter <ctboughter@gmail.com>
Project-URL: Homepage, https://github.com/ctboughter/aims
Project-URL: Bug Tracker, https://github.com/ctboughter/aims/issues
Classifier: Programming Language :: Python :: 3
Classifier: License :: OSI Approved :: MIT License
Classifier: Operating System :: OS Independent
Requires-Python: <=3.9
License-File: LICENSE
Requires-Dist: requests
Requires-Dist: kivy >=2.1.0
Requires-Dist: umap-learn ==0.5.3
Requires-Dist: biopython >=1.76
Requires-Dist: scipy >=1.4.1
Requires-Dist: pandas >=1.0.3
Requires-Dist: numpy >=1.18.1
Requires-Dist: matplotlib >=3.1.3
Requires-Dist: scikit-learn >=0.22.1
Requires-Dist: seaborn >=0.10.1
Requires-Dist: jupyterlab >=3.1.12
Requires-Dist: ipython >=7.27.0
Requires-Dist: ipykernel >=5.5.5
Requires-Dist: importlib-metadata ; python_version < "3.9"
